{
    "info": {
        "year": 2022,
        "version": "1.0",
        "description": "VIA project exported to COCO format using VGG Image Annotator (http://www.robots.ox.ac.uk/~vgg/software/via/)",
        "contributor": "",
        "url": "http://www.robots.ox.ac.uk/~vgg/software/via/",
        "date_created": "Fri Feb 18 2022 03:44:22 GMT+0100 (Central European Standard Time)"
    },
    "images": [
        {
            "id": 1,
            "width": 962,
            "height": 411,
            "file_name": "image64.jpg",
            "license": 0,
            "date_captured": ""
        }
    ],
    "annotations": [
        {
            "segmentation": [
                [
                    260,
                    361,
                    281,
                    359,
                    305,
                    346,
                    320,
                    330,
                    330,
                    307,
                    330,
                    286,
                    325,
                    267,
                    315,
                    246,
                    301,
                    234,
                    286,
                    227,
                    268,
                    222,
                    249,
                    222,
                    233,
                    226,
                    218,
                    234,
                    206,
                    245,
                    194,
                    260,
                    188,
                    275,
                    185,
                    290,
                    186,
                    304,
                    190,
                    323,
                    199,
                    335,
                    209,
                    344,
                    220,
                    353,
                    239,
                    361
                ]
            ],
            "area": 20155,
            "bbox": [
                185,
                222,
                145,
                139
            ],
            "iscrowd": 0,
            "id": 1,
            "image_id": 1,
            "category_id": 4
        },
        {
            "segmentation": [
                [
                    800,
                    333,
                    823,
                    328,
                    840,
                    318,
                    853,
                    303,
                    861,
                    283,
                    865,
                    266,
                    863,
                    246,
                    854,
                    224,
                    839,
                    205,
                    827,
                    196,
                    810,
                    190,
                    790,
                    188,
                    769,
                    190,
                    754,
                    197,
                    743,
                    205,
                    732,
                    216,
                    722,
                    231,
                    719,
                    247,
                    717,
                    261,
                    720,
                    284,
                    725,
                    298,
                    736,
                    310,
                    753,
                    323,
                    776,
                    331
                ]
            ],
            "area": 21460,
            "bbox": [
                717,
                188,
                148,
                145
            ],
            "iscrowd": 0,
            "id": 2,
            "image_id": 1,
            "category_id": 4
        },
        {
            "segmentation": [
                [
                    374,
                    299,
                    421,
                    296,
                    466,
                    293,
                    531,
                    289,
                    564,
                    285,
                    588,
                    279,
                    599,
                    271,
                    616,
                    251,
                    633,
                    218,
                    642,
                    194,
                    643,
                    181,
                    641,
                    169,
                    637,
                    158,
                    634,
                    155,
                    626,
                    149,
                    612,
                    151,
                    575,
                    154,
                    522,
                    160,
                    470,
                    164,
                    450,
                    165,
                    424,
                    167,
                    403,
                    169,
                    395,
                    170,
                    387,
                    174,
                    378,
                    183,
                    371,
                    192,
                    368,
                    199,
                    365,
                    211,
                    365,
                    224,
                    366,
                    239,
                    369,
                    254,
                    372,
                    278
                ]
            ],
            "area": 41700,
            "bbox": [
                365,
                149,
                278,
                150
            ],
            "iscrowd": 0,
            "id": 3,
            "image_id": 1,
            "category_id": 8
        },
        {
            "segmentation": [
                [
                    109,
                    243,
                    122,
                    243,
                    136,
                    235,
                    149,
                    224,
                    167,
                    213,
                    182,
                    201,
                    187,
                    195,
                    185,
                    191,
                    178,
                    191,
                    168,
                    195,
                    161,
                    199,
                    152,
                    205,
                    139,
                    214,
                    127,
                    224,
                    118,
                    231,
                    111,
                    239
                ]
            ],
            "area": 4056,
            "bbox": [
                109,
                191,
                78,
                52
            ],
            "iscrowd": 0,
            "id": 4,
            "image_id": 1,
            "category_id": 6
        },
        {
            "segmentation": [
                [
                    165,
                    232,
                    186,
                    233,
                    200,
                    233,
                    218,
                    221,
                    231,
                    216,
                    252,
                    212,
                    276,
                    214,
                    289,
                    218,
                    300,
                    221,
                    309,
                    230,
                    318,
                    235,
                    328,
                    248,
                    330,
                    252,
                    335,
                    261,
                    338,
                    274,
                    345,
                    300,
                    359,
                    300,
                    374,
                    299,
                    369,
                    257,
                    366,
                    236,
                    365,
                    208,
                    370,
                    193,
                    381,
                    179,
                    395,
                    170,
                    383,
                    169,
                    363,
                    171,
                    335,
                    173,
                    311,
                    175,
                    291,
                    177,
                    265,
                    178,
                    243,
                    181,
                    220,
                    185,
                    208,
                    188,
                    189,
                    193,
                    189,
                    196,
                    178,
                    205,
                    167,
                    215,
                    153,
                    222,
                    143,
                    232,
                    147,
                    233,
                    156,
                    234
                ]
            ],
            "area": 33012,
            "bbox": [
                143,
                169,
                252,
                131
            ],
            "iscrowd": 0,
            "id": 5,
            "image_id": 1,
            "category_id": 5
        },
        {
            "segmentation": [
                [
                    464,
                    123,
                    445,
                    138,
                    441,
                    139,
                    443,
                    145,
                    444,
                    152,
                    444,
                    160,
                    443,
                    165,
                    485,
                    163,
                    546,
                    157,
                    620,
                    150,
                    622,
                    141,
                    622,
                    126,
                    620,
                    117,
                    615,
                    110,
                    598,
                    103,
                    583,
                    100,
                    562,
                    97,
                    547,
                    97,
                    532,
                    99,
                    515,
                    101,
                    500,
                    104,
                    487,
                    109
                ]
            ],
            "area": 12308,
            "bbox": [
                441,
                97,
                181,
                68
            ],
            "iscrowd": 0,
            "id": 6,
            "image_id": 1,
            "category_id": 9
        },
        {
            "segmentation": [
                [
                    854,
                    165,
                    866,
                    172,
                    883,
                    175,
                    911,
                    176,
                    923,
                    175,
                    924,
                    167,
                    924,
                    159,
                    926,
                    154,
                    922,
                    154,
                    913,
                    155,
                    904,
                    155,
                    897,
                    150,
                    885,
                    145,
                    871,
                    141,
                    863,
                    144,
                    852,
                    150,
                    846,
                    154,
                    845,
                    159
                ]
            ],
            "area": 2835,
            "bbox": [
                845,
                141,
                81,
                35
            ],
            "iscrowd": 0,
            "id": 7,
            "image_id": 1,
            "category_id": 7
        },
        {
            "segmentation": [
                [
                    682,
                    181,
                    709,
                    180,
                    728,
                    181,
                    743,
                    185,
                    753,
                    188,
                    745,
                    193,
                    736,
                    198,
                    728,
                    206,
                    716,
                    224,
                    712,
                    233,
                    710,
                    243,
                    708,
                    262,
                    706,
                    277,
                    707,
                    289,
                    710,
                    302,
                    709,
                    304,
                    683,
                    308,
                    640,
                    313,
                    592,
                    317,
                    530,
                    319,
                    401,
                    326,
                    344,
                    330,
                    345,
                    320,
                    345,
                    301,
                    382,
                    299,
                    456,
                    294,
                    526,
                    290,
                    559,
                    286,
                    589,
                    278,
                    601,
                    271,
                    618,
                    250,
                    625,
                    235,
                    634,
                    216,
                    643,
                    194,
                    643,
                    184
                ]
            ],
            "area": 61350,
            "bbox": [
                344,
                180,
                409,
                150
            ],
            "iscrowd": 0,
            "id": 8,
            "image_id": 1,
            "category_id": 5
        },
        {
            "segmentation": [
                [
                    825,
                    185,
                    839,
                    191,
                    850,
                    199,
                    860,
                    213,
                    869,
                    229,
                    874,
                    244,
                    877,
                    264,
                    874,
                    289,
                    904,
                    281,
                    932,
                    271,
                    947,
                    259,
                    955,
                    250,
                    951,
                    238,
                    951,
                    232,
                    948,
                    229,
                    946,
                    220,
                    946,
                    206,
                    947,
                    195,
                    947,
                    186,
                    944,
                    179,
                    938,
                    171,
                    931,
                    166,
                    928,
                    159,
                    927,
                    155,
                    924,
                    161,
                    924,
                    175,
                    910,
                    178,
                    890,
                    176,
                    865,
                    172,
                    837,
                    180
                ]
            ],
            "area": 17420,
            "bbox": [
                825,
                155,
                130,
                134
            ],
            "iscrowd": 0,
            "id": 9,
            "image_id": 1,
            "category_id": 12
        },
        {
            "segmentation": [
                [
                    182,
                    256,
                    178,
                    271,
                    177,
                    281,
                    177,
                    288,
                    180,
                    306,
                    182,
                    320,
                    187,
                    345,
                    159,
                    348,
                    134,
                    347,
                    119,
                    349,
                    104,
                    331,
                    90,
                    326,
                    72,
                    324,
                    63,
                    322,
                    65,
                    318,
                    67,
                    316,
                    67,
                    303,
                    68,
                    289,
                    62,
                    290,
                    62,
                    264,
                    65,
                    261,
                    75,
                    248,
                    89,
                    237,
                    113,
                    224,
                    149,
                    206,
                    136,
                    218,
                    118,
                    231,
                    108,
                    242,
                    122,
                    244,
                    134,
                    237,
                    142,
                    232,
                    157,
                    235,
                    165,
                    233,
                    197,
                    234,
                    186,
                    249
                ]
            ],
            "area": 19305,
            "bbox": [
                62,
                206,
                135,
                143
            ],
            "iscrowd": 0,
            "id": 10,
            "image_id": 1,
            "category_id": 3
        },
        {
            "segmentation": [
                [
                    466,
                    85,
                    471,
                    88,
                    477,
                    91,
                    481,
                    100,
                    482,
                    111,
                    496,
                    105,
                    515,
                    101,
                    549,
                    97,
                    564,
                    97,
                    601,
                    104,
                    617,
                    110,
                    622,
                    122,
                    623,
                    133,
                    620,
                    149,
                    648,
                    148,
                    699,
                    141,
                    736,
                    134,
                    746,
                    130,
                    746,
                    127,
                    741,
                    121,
                    732,
                    117,
                    710,
                    107,
                    674,
                    90,
                    666,
                    86,
                    651,
                    77,
                    623,
                    73,
                    590,
                    71,
                    545,
                    74,
                    501,
                    78
                ]
            ],
            "area": 21840,
            "bbox": [
                466,
                71,
                280,
                78
            ],
            "iscrowd": 0,
            "id": 11,
            "image_id": 1,
            "category_id": 11
        },
        {
            "segmentation": [
                [
                    754,
                    187,
                    769,
                    182,
                    786,
                    179,
                    801,
                    180,
                    818,
                    181,
                    824,
                    186,
                    844,
                    179,
                    865,
                    172,
                    844,
                    159,
                    846,
                    155,
                    870,
                    141,
                    850,
                    137,
                    820,
                    134,
                    791,
                    133,
                    758,
                    134,
                    739,
                    136,
                    724,
                    137,
                    680,
                    144,
                    651,
                    148,
                    626,
                    149,
                    638,
                    159,
                    644,
                    183,
                    684,
                    181,
                    714,
                    179,
                    730,
                    181
                ]
            ],
            "area": 13176,
            "bbox": [
                626,
                133,
                244,
                54
            ],
            "iscrowd": 0,
            "id": 12,
            "image_id": 1,
            "category_id": 5
        },
        {
            "segmentation": [
                [
                    457,
                    89,
                    465,
                    92,
                    471,
                    98,
                    471,
                    102,
                    461,
                    109,
                    450,
                    117,
                    429,
                    128,
                    411,
                    139,
                    389,
                    154,
                    379,
                    161,
                    371,
                    167,
                    365,
                    166,
                    352,
                    163,
                    340,
                    161,
                    329,
                    159,
                    358,
                    147,
                    393,
                    126
                ]
            ],
            "area": 11076,
            "bbox": [
                329,
                89,
                142,
                78
            ],
            "iscrowd": 0,
            "id": 13,
            "image_id": 1,
            "category_id": 9
        },
        {
            "segmentation": [
                [
                    301,
                    163,
                    259,
                    170,
                    221,
                    178,
                    194,
                    186,
                    186,
                    190,
                    189,
                    193,
                    246,
                    180,
                    266,
                    177,
                    310,
                    174,
                    369,
                    169,
                    328,
                    159,
                    315,
                    162
                ]
            ],
            "area": 6222,
            "bbox": [
                186,
                159,
                183,
                34
            ],
            "iscrowd": 0,
            "id": 14,
            "image_id": 1,
            "category_id": 1
        },
        {
            "segmentation": [
                [
                    432,
                    129,
                    436,
                    130,
                    439,
                    136,
                    441,
                    139,
                    443,
                    146,
                    444,
                    153,
                    443,
                    162,
                    443,
                    165,
                    436,
                    166,
                    424,
                    167,
                    421,
                    164,
                    419,
                    158,
                    420,
                    151,
                    424,
                    148,
                    428,
                    143,
                    430,
                    140
                ]
            ],
            "area": 950,
            "bbox": [
                419,
                129,
                25,
                38
            ],
            "iscrowd": 0,
            "id": 15,
            "image_id": 1,
            "category_id": 2
        },
        {
            "segmentation": [
                [
                    371,
                    169,
                    383,
                    169,
                    395,
                    170,
                    407,
                    168,
                    420,
                    156,
                    419,
                    151,
                    425,
                    147,
                    430,
                    141,
                    432,
                    129,
                    436,
                    130,
                    441,
                    139,
                    445,
                    138,
                    466,
                    122,
                    482,
                    111,
                    481,
                    100,
                    476,
                    91,
                    466,
                    85,
                    458,
                    89,
                    465,
                    92,
                    471,
                    98,
                    471,
                    102,
                    466,
                    106,
                    427,
                    130,
                    393,
                    151,
                    372,
                    166
                ]
            ],
            "area": 9435,
            "bbox": [
                371,
                85,
                111,
                85
            ],
            "iscrowd": 0,
            "id": 16,
            "image_id": 1,
            "category_id": 14
        },
        {
            "segmentation": [
                [
                    741,
                    120,
                    746,
                    127,
                    746,
                    131,
                    734,
                    134,
                    724,
                    136,
                    738,
                    136,
                    758,
                    134,
                    791,
                    133,
                    825,
                    134,
                    864,
                    140,
                    882,
                    144,
                    898,
                    150,
                    904,
                    155,
                    908,
                    154,
                    900,
                    149,
                    889,
                    144,
                    862,
                    137,
                    832,
                    131,
                    762,
                    122,
                    753,
                    121
                ]
            ],
            "area": 6440,
            "bbox": [
                724,
                120,
                184,
                35
            ],
            "iscrowd": 0,
            "id": 17,
            "image_id": 1,
            "category_id": 10
        },
        {
            "segmentation": [
                [
                    898,
                    147,
                    909,
                    145,
                    916,
                    145,
                    921,
                    145,
                    926,
                    146,
                    928,
                    148,
                    928,
                    151,
                    928,
                    154,
                    926,
                    155,
                    925,
                    154,
                    910,
                    155,
                    905,
                    152,
                    896,
                    147
                ]
            ],
            "area": 320,
            "bbox": [
                896,
                145,
                32,
                10
            ],
            "iscrowd": 0,
            "id": 18,
            "image_id": 1,
            "category_id": 13
        },
        {
            "segmentation": [
                [
                    402,
                    192,
                    413,
                    201,
                    431,
                    205,
                    441,
                    197,
                    452,
                    179,
                    447,
                    171,
                    441,
                    164,
                    443,
                    149,
                    439,
                    134,
                    433,
                    128,
                    429,
                    140,
                    419,
                    153,
                    421,
                    159,
                    422,
                    166,
                    429,
                    167,
                    422,
                    173,
                    412,
                    175,
                    405,
                    175,
                    400,
                    181,
                    400,
                    187
                ]
            ],
            "area": 4004,
            "bbox": [
                400,
                128,
                52,
                77
            ],
            "iscrowd": 0,
            "id": 19,
            "image_id": 1,
            "category_id": 15
        },
        {
            "segmentation": [
                [
                    511,
                    247,
                    535,
                    244,
                    536,
                    237,
                    531,
                    233,
                    512,
                    227,
                    509,
                    233
                ]
            ],
            "area": 540,
            "bbox": [
                509,
                227,
                27,
                20
            ],
            "iscrowd": 0,
            "id": 20,
            "image_id": 1,
            "category_id": 15
        },
        {
            "segmentation": [
                [
                    386,
                    223,
                    408,
                    222,
                    403,
                    212,
                    393,
                    209,
                    384,
                    220
                ]
            ],
            "area": 336,
            "bbox": [
                384,
                209,
                24,
                14
            ],
            "iscrowd": 0,
            "id": 21,
            "image_id": 1,
            "category_id": 15
        },
        {
            "segmentation": [
                [
                    267,
                    205,
                    299,
                    213,
                    315,
                    223,
                    331,
                    240,
                    341,
                    236,
                    355,
                    225,
                    341,
                    207,
                    331,
                    185,
                    311,
                    181,
                    291,
                    186,
                    272,
                    189,
                    272,
                    193
                ]
            ],
            "area": 5192,
            "bbox": [
                267,
                181,
                88,
                59
            ],
            "iscrowd": 0,
            "id": 22,
            "image_id": 1,
            "category_id": 15
        },
        {
            "segmentation": [
                [
                    195,
                    230,
                    206,
                    221,
                    222,
                    214,
                    228,
                    211,
                    233,
                    202,
                    227,
                    192,
                    217,
                    189,
                    208,
                    190,
                    193,
                    193,
                    190,
                    195,
                    190,
                    196,
                    177,
                    206,
                    168,
                    215,
                    154,
                    221,
                    155,
                    225,
                    166,
                    229,
                    178,
                    229
                ]
            ],
            "area": 3239,
            "bbox": [
                154,
                189,
                79,
                41
            ],
            "iscrowd": 0,
            "id": 23,
            "image_id": 1,
            "category_id": 15
        },
        {
            "segmentation": [
                [
                    122,
                    295,
                    135,
                    301,
                    154,
                    303,
                    168,
                    306,
                    177,
                    311,
                    180,
                    319,
                    184,
                    332,
                    186,
                    344,
                    158,
                    346,
                    138,
                    347,
                    126,
                    347,
                    117,
                    349,
                    113,
                    343,
                    109,
                    348,
                    103,
                    348,
                    93,
                    337,
                    103,
                    332,
                    97,
                    329,
                    91,
                    329,
                    87,
                    329,
                    90,
                    338,
                    93,
                    348,
                    96,
                    362,
                    90,
                    363,
                    86,
                    345,
                    82,
                    337,
                    79,
                    326,
                    77,
                    322,
                    67,
                    322,
                    67,
                    315,
                    69,
                    306,
                    82,
                    309,
                    97,
                    309,
                    109,
                    304
                ]
            ],
            "area": 8092,
            "bbox": [
                67,
                295,
                119,
                68
            ],
            "iscrowd": 0,
            "id": 24,
            "image_id": 1,
            "category_id": 15
        },
        {
            "segmentation": [
                [
                    113,
                    263,
                    140,
                    262,
                    158,
                    260,
                    163,
                    242,
                    162,
                    236,
                    144,
                    234,
                    136,
                    238,
                    120,
                    248,
                    114,
                    253
                ]
            ],
            "area": 1450,
            "bbox": [
                113,
                234,
                50,
                29
            ],
            "iscrowd": 0,
            "id": 25,
            "image_id": 1,
            "category_id": 15
        },
        {
            "segmentation": [
                [
                    449,
                    246,
                    464,
                    245,
                    470,
                    243,
                    464,
                    241,
                    450,
                    243
                ]
            ],
            "area": 105,
            "bbox": [
                449,
                241,
                21,
                5
            ],
            "iscrowd": 0,
            "id": 26,
            "image_id": 1,
            "category_id": 15
        },
        {
            "segmentation": [
                [
                    386,
                    271,
                    395,
                    279,
                    400,
                    291,
                    406,
                    295,
                    414,
                    292,
                    419,
                    282,
                    415,
                    266,
                    393,
                    263
                ]
            ],
            "area": 1056,
            "bbox": [
                386,
                263,
                33,
                32
            ],
            "iscrowd": 0,
            "id": 27,
            "image_id": 1,
            "category_id": 15
        },
        {
            "segmentation": [
                [
                    518,
                    207,
                    521,
                    211,
                    533,
                    211,
                    542,
                    206,
                    552,
                    200,
                    558,
                    196,
                    553,
                    185,
                    542,
                    177,
                    524,
                    176,
                    517,
                    189,
                    515,
                    196
                ]
            ],
            "area": 1505,
            "bbox": [
                515,
                176,
                43,
                35
            ],
            "iscrowd": 0,
            "id": 28,
            "image_id": 1,
            "category_id": 15
        },
        {
            "segmentation": [
                [
                    566,
                    208,
                    573,
                    212,
                    579,
                    212,
                    591,
                    207,
                    580,
                    204,
                    566,
                    204
                ]
            ],
            "area": 200,
            "bbox": [
                566,
                204,
                25,
                8
            ],
            "iscrowd": 0,
            "id": 29,
            "image_id": 1,
            "category_id": 15
        },
        {
            "segmentation": [
                [
                    544,
                    224,
                    557,
                    219,
                    562,
                    220,
                    556,
                    232,
                    544,
                    238,
                    537,
                    238,
                    531,
                    233,
                    537,
                    227,
                    532,
                    222,
                    536,
                    220
                ]
            ],
            "area": 589,
            "bbox": [
                531,
                219,
                31,
                19
            ],
            "iscrowd": 0,
            "id": 30,
            "image_id": 1,
            "category_id": 15
        }
    ],
    "licenses": [
        {
            "id": 0,
            "name": "Unknown License",
            "url": ""
        }
    ],
    "categories": [
        {
            "supercategory": "part",
            "id": 0,
            "name": "BG"
        },
        {
            "supercategory": "part",
            "id": 1,
            "name": "hood"
        },
        {
            "supercategory": "part",
            "id": 2,
            "name": "mirror"
        },
        {
            "supercategory": "part",
            "id": 3,
            "name": "bumper"
        },
        {
            "supercategory": "part",
            "id": 4,
            "name": "wheel"
        },
        {
            "supercategory": "part",
            "id": 5,
            "name": "fender"
        },
        {
            "supercategory": "part",
            "id": 6,
            "name": "headlight"
        },
        {
            "supercategory": "part",
            "id": 7,
            "name": "tail light"
        },
        {
            "supercategory": "part",
            "id": 8,
            "name": "door"
        },
        {
            "supercategory": "part",
            "id": 9,
            "name": "glass"
        },
        {
            "supercategory": "part",
            "id": 10,
            "name": "trunk"
        },
        {
            "supercategory": "part",
            "id": 11,
            "name": "roof"
        },
        {
            "supercategory": "part",
            "id": 12,
            "name": "rear bumper"
        },
        {
            "supercategory": "part",
            "id": 13,
            "name": "spoiler"
        },
        {
            "supercategory": "part",
            "id": 14,
            "name": "frame"
        },
        {
            "supercategory": "damage",
            "id": 15,
            "name": "BG"
        },
        {
            "supercategory": "damage",
            "id": 16,
            "name": "damage"
        }
    ]
}